{"errors":[],"sptypes":[{"ann":"GHC.Types.Module","ident":"InterfaceAdapters.AgricultureRestService.$trModule","start":{"column":1,"line":1},"stop":{"column":1,"line":1}},{"ann":"forall a .\n(GHC.Classes.(%,%)<[]> (Polysemy.Internal.Union.Find ((TYPE 'GHC.Types.LiftedRep) -> (TYPE 'GHC.Types.LiftedRep)) -> (TYPE 'GHC.Types.LiftedRep) -> (TYPE 'GHC.Types.LiftedRep) (Polysemy.Embed.Type.Embed GHC.Types.IO) a) (GHC.Types.~ () (Polysemy.Internal.Union.LocateEffect ((TYPE 'GHC.Types.LiftedRep) -> (TYPE 'GHC.Types.LiftedRep)) -> (TYPE 'GHC.Types.LiftedRep) -> (TYPE 'GHC.Types.LiftedRep) (Polysemy.Embed.Type.Embed GHC.Types.IO) a) '()), GHC.Classes.(%,%)<[]> (Polysemy.Internal.Union.Find ((TYPE 'GHC.Types.LiftedRep) -> (TYPE 'GHC.Types.LiftedRep)) -> (TYPE 'GHC.Types.LiftedRep) -> (TYPE 'GHC.Types.LiftedRep) (UseCases.WWI.WWI (TYPE 'GHC.Types.LiftedRep) -> (TYPE 'GHC.Types.LiftedRep)) a) (GHC.Types.~ () (Polysemy.Internal.Union.LocateEffect ((TYPE 'GHC.Types.LiftedRep) -> (TYPE 'GHC.Types.LiftedRep)) -> (TYPE 'GHC.Types.LiftedRep) -> (TYPE 'GHC.Types.LiftedRep) (UseCases.WWI.WWI (TYPE 'GHC.Types.LiftedRep) -> (TYPE 'GHC.Types.LiftedRep)) a) '())) =>\n(Servant.Server.Internal.ServerT (TYPE 'GHC.Types.LiftedRep) (Servant.API.Alternative.:<|> (Servant.API.Sub.:> (TYPE 'GHC.Types.LiftedRep) (Servant.API.Description.Summary [GHC.Types.Char]) (Servant.API.Sub.:> (TYPE 'GHC.Types.LiftedRep) (Servant.API.ReqBody.ReqBody' (': (TYPE 'GHC.Types.LiftedRep) Servant.API.Modifiers.Required (': (TYPE 'GHC.Types.LiftedRep) Servant.API.Modifiers.Strict ('[] (TYPE 'GHC.Types.LiftedRep)))) (': (TYPE 'GHC.Types.LiftedRep) Servant.API.ContentTypes.JSON ('[] (TYPE 'GHC.Types.LiftedRep))) Web.Telegram.API.Bot.Data.Update) (Servant.API.Verbs.Verb Network.HTTP.Types.Method.StdMethod 'Network.HTTP.Types.Method.POST GHC.Types.Int (': (TYPE 'GHC.Types.LiftedRep) Servant.API.ContentTypes.PlainText ('[] (TYPE 'GHC.Types.LiftedRep))) Data.Text.Internal.Text))) (Servant.API.Sub.:> (TYPE 'GHC.Types.LiftedRep) (Servant.API.Description.Summary [GHC.Types.Char]) (Servant.API.Sub.:> (TYPE 'GHC.Types.LiftedRep) (Servant.API.ReqBody.ReqBody' (': (TYPE 'GHC.Types.LiftedRep) Servant.API.Modifiers.Required (': (TYPE 'GHC.Types.LiftedRep) Servant.API.Modifiers.Strict ('[] (TYPE 'GHC.Types.LiftedRep)))) (': (TYPE 'GHC.Types.LiftedRep) Servant.API.ContentTypes.PlainText ('[] (TYPE 'GHC.Types.LiftedRep))) Data.Text.Internal.Text) (Servant.API.Verbs.Verb Network.HTTP.Types.Method.StdMethod 'Network.HTTP.Types.Method.POST GHC.Types.Int (': (TYPE 'GHC.Types.LiftedRep) Servant.API.ContentTypes.PlainText ('[] (TYPE 'GHC.Types.LiftedRep))) Data.Text.Internal.Text)))) (Polysemy.Internal.Sem a))","ident":"InterfaceAdapters.AgricultureRestService.agricultureServer","start":{"column":1,"line":40},"stop":{"column":18,"line":40}},{"ann":"Web.Telegram.API.Bot.Data.Update -> (Polysemy.Internal.Sem a Data.Text.Internal.Text)","ident":"lq_anf$##7205759403794028761","start":{"column":22,"line":40},"stop":{"column":32,"line":40}},{"ann":"Data.Text.Internal.Text -> (Polysemy.Internal.Sem a Data.Text.Internal.Text)","ident":"lq_anf$##7205759403794028762","start":{"column":39,"line":40},"stop":{"column":49,"line":40}},{"ann":"(Data.Proxy.Proxy (TYPE 'GHC.Types.LiftedRep) (Servant.API.Alternative.:<|> (Servant.API.Sub.:> (TYPE 'GHC.Types.LiftedRep) (Servant.API.Description.Summary [GHC.Types.Char]) (Servant.API.Sub.:> (TYPE 'GHC.Types.LiftedRep) (Servant.API.ReqBody.ReqBody' (': (TYPE 'GHC.Types.LiftedRep) Servant.API.Modifiers.Required (': (TYPE 'GHC.Types.LiftedRep) Servant.API.Modifiers.Strict ('[] (TYPE 'GHC.Types.LiftedRep)))) (': (TYPE 'GHC.Types.LiftedRep) Servant.API.ContentTypes.JSON ('[] (TYPE 'GHC.Types.LiftedRep))) Web.Telegram.API.Bot.Data.Update) (Servant.API.Verbs.Verb Network.HTTP.Types.Method.StdMethod 'Network.HTTP.Types.Method.POST GHC.Types.Int (': (TYPE 'GHC.Types.LiftedRep) Servant.API.ContentTypes.PlainText ('[] (TYPE 'GHC.Types.LiftedRep))) Data.Text.Internal.Text))) (Servant.API.Sub.:> (TYPE 'GHC.Types.LiftedRep) (Servant.API.Description.Summary [GHC.Types.Char]) (Servant.API.Sub.:> (TYPE 'GHC.Types.LiftedRep) (Servant.API.ReqBody.ReqBody' (': (TYPE 'GHC.Types.LiftedRep) Servant.API.Modifiers.Required (': (TYPE 'GHC.Types.LiftedRep) Servant.API.Modifiers.Strict ('[] (TYPE 'GHC.Types.LiftedRep)))) (': (TYPE 'GHC.Types.LiftedRep) Servant.API.ContentTypes.PlainText ('[] (TYPE 'GHC.Types.LiftedRep))) Data.Text.Internal.Text) (Servant.API.Verbs.Verb Network.HTTP.Types.Method.StdMethod 'Network.HTTP.Types.Method.POST GHC.Types.Int (': (TYPE 'GHC.Types.LiftedRep) Servant.API.ContentTypes.PlainText ('[] (TYPE 'GHC.Types.LiftedRep))) Data.Text.Internal.Text)))))","ident":"InterfaceAdapters.AgricultureRestService.agricultureAPI","start":{"column":1,"line":44},"stop":{"column":15,"line":44}}],"status":"safe","types":{"1":{"1":{"ann":"GHC.Types.Module","col":1,"ident":"InterfaceAdapters.AgricultureRestService.$trModule","row":1}},"40":{"1":{"ann":"forall a .\n(GHC.Classes.(%,%)<[]> (Polysemy.Internal.Union.Find ((TYPE 'GHC.Types.LiftedRep) -> (TYPE 'GHC.Types.LiftedRep)) -> (TYPE 'GHC.Types.LiftedRep) -> (TYPE 'GHC.Types.LiftedRep) (Polysemy.Embed.Type.Embed GHC.Types.IO) a) (GHC.Types.~ () (Polysemy.Internal.Union.LocateEffect ((TYPE 'GHC.Types.LiftedRep) -> (TYPE 'GHC.Types.LiftedRep)) -> (TYPE 'GHC.Types.LiftedRep) -> (TYPE 'GHC.Types.LiftedRep) (Polysemy.Embed.Type.Embed GHC.Types.IO) a) '()), GHC.Classes.(%,%)<[]> (Polysemy.Internal.Union.Find ((TYPE 'GHC.Types.LiftedRep) -> (TYPE 'GHC.Types.LiftedRep)) -> (TYPE 'GHC.Types.LiftedRep) -> (TYPE 'GHC.Types.LiftedRep) (UseCases.WWI.WWI (TYPE 'GHC.Types.LiftedRep) -> (TYPE 'GHC.Types.LiftedRep)) a) (GHC.Types.~ () (Polysemy.Internal.Union.LocateEffect ((TYPE 'GHC.Types.LiftedRep) -> (TYPE 'GHC.Types.LiftedRep)) -> (TYPE 'GHC.Types.LiftedRep) -> (TYPE 'GHC.Types.LiftedRep) (UseCases.WWI.WWI (TYPE 'GHC.Types.LiftedRep) -> (TYPE 'GHC.Types.LiftedRep)) a) '())) =>\n(Servant.Server.Internal.ServerT (TYPE 'GHC.Types.LiftedRep) (Servant.API.Alternative.:<|> (Servant.API.Sub.:> (TYPE 'GHC.Types.LiftedRep) (Servant.API.Description.Summary [GHC.Types.Char]) (Servant.API.Sub.:> (TYPE 'GHC.Types.LiftedRep) (Servant.API.ReqBody.ReqBody' (': (TYPE 'GHC.Types.LiftedRep) Servant.API.Modifiers.Required (': (TYPE 'GHC.Types.LiftedRep) Servant.API.Modifiers.Strict ('[] (TYPE 'GHC.Types.LiftedRep)))) (': (TYPE 'GHC.Types.LiftedRep) Servant.API.ContentTypes.JSON ('[] (TYPE 'GHC.Types.LiftedRep))) Web.Telegram.API.Bot.Data.Update) (Servant.API.Verbs.Verb Network.HTTP.Types.Method.StdMethod 'Network.HTTP.Types.Method.POST GHC.Types.Int (': (TYPE 'GHC.Types.LiftedRep) Servant.API.ContentTypes.PlainText ('[] (TYPE 'GHC.Types.LiftedRep))) Data.Text.Internal.Text))) (Servant.API.Sub.:> (TYPE 'GHC.Types.LiftedRep) (Servant.API.Description.Summary [GHC.Types.Char]) (Servant.API.Sub.:> (TYPE 'GHC.Types.LiftedRep) (Servant.API.ReqBody.ReqBody' (': (TYPE 'GHC.Types.LiftedRep) Servant.API.Modifiers.Required (': (TYPE 'GHC.Types.LiftedRep) Servant.API.Modifiers.Strict ('[] (TYPE 'GHC.Types.LiftedRep)))) (': (TYPE 'GHC.Types.LiftedRep) Servant.API.ContentTypes.PlainText ('[] (TYPE 'GHC.Types.LiftedRep))) Data.Text.Internal.Text) (Servant.API.Verbs.Verb Network.HTTP.Types.Method.StdMethod 'Network.HTTP.Types.Method.POST GHC.Types.Int (': (TYPE 'GHC.Types.LiftedRep) Servant.API.ContentTypes.PlainText ('[] (TYPE 'GHC.Types.LiftedRep))) Data.Text.Internal.Text)))) (Polysemy.Internal.Sem a))","col":1,"ident":"InterfaceAdapters.AgricultureRestService.agricultureServer","row":40},"22":{"ann":"Web.Telegram.API.Bot.Data.Update -> (Polysemy.Internal.Sem a Data.Text.Internal.Text)","col":22,"ident":"lq_anf$##7205759403794028761","row":40},"39":{"ann":"Data.Text.Internal.Text -> (Polysemy.Internal.Sem a Data.Text.Internal.Text)","col":39,"ident":"lq_anf$##7205759403794028762","row":40}},"44":{"1":{"ann":"(Data.Proxy.Proxy (TYPE 'GHC.Types.LiftedRep) (Servant.API.Alternative.:<|> (Servant.API.Sub.:> (TYPE 'GHC.Types.LiftedRep) (Servant.API.Description.Summary [GHC.Types.Char]) (Servant.API.Sub.:> (TYPE 'GHC.Types.LiftedRep) (Servant.API.ReqBody.ReqBody' (': (TYPE 'GHC.Types.LiftedRep) Servant.API.Modifiers.Required (': (TYPE 'GHC.Types.LiftedRep) Servant.API.Modifiers.Strict ('[] (TYPE 'GHC.Types.LiftedRep)))) (': (TYPE 'GHC.Types.LiftedRep) Servant.API.ContentTypes.JSON ('[] (TYPE 'GHC.Types.LiftedRep))) Web.Telegram.API.Bot.Data.Update) (Servant.API.Verbs.Verb Network.HTTP.Types.Method.StdMethod 'Network.HTTP.Types.Method.POST GHC.Types.Int (': (TYPE 'GHC.Types.LiftedRep) Servant.API.ContentTypes.PlainText ('[] (TYPE 'GHC.Types.LiftedRep))) Data.Text.Internal.Text))) (Servant.API.Sub.:> (TYPE 'GHC.Types.LiftedRep) (Servant.API.Description.Summary [GHC.Types.Char]) (Servant.API.Sub.:> (TYPE 'GHC.Types.LiftedRep) (Servant.API.ReqBody.ReqBody' (': (TYPE 'GHC.Types.LiftedRep) Servant.API.Modifiers.Required (': (TYPE 'GHC.Types.LiftedRep) Servant.API.Modifiers.Strict ('[] (TYPE 'GHC.Types.LiftedRep)))) (': (TYPE 'GHC.Types.LiftedRep) Servant.API.ContentTypes.PlainText ('[] (TYPE 'GHC.Types.LiftedRep))) Data.Text.Internal.Text) (Servant.API.Verbs.Verb Network.HTTP.Types.Method.StdMethod 'Network.HTTP.Types.Method.POST GHC.Types.Int (': (TYPE 'GHC.Types.LiftedRep) Servant.API.ContentTypes.PlainText ('[] (TYPE 'GHC.Types.LiftedRep))) Data.Text.Internal.Text)))))","col":1,"ident":"InterfaceAdapters.AgricultureRestService.agricultureAPI","row":44}}}}